set_mcp/__init__.py
set_mcp/__main__.py
set_mcp/py.typed
set_mcp/settrade_scraper.py
set_mcp-0.3.0.dist-info/METADATA
set_mcp-0.3.0.dist-info/WHEEL
set_mcp-0.3.0.dist-info/entry_points.txt
set_mcp-0.3.0.dist-info/RECORD
