Metadata-Version: 2.4
Name: set-mcp
Version: 0.3.0
Summary: Add your description here
Author-email: prem <prem.ch@ku.th>
Requires-Python: >=3.11
Requires-Dist: fastmcp>=2.1.1
Requires-Dist: httpx>=0.28.1
Requires-Dist: pandas>=2.2.3
